discordmc/__init__.py
discordmc/__main__.py
discordmc/bot.py
discordmc/cli.py
DiscordMC-0.0.8.dist-info/METADATA
DiscordMC-0.0.8.dist-info/WHEEL
DiscordMC-0.0.8.dist-info/top_level.txt
DiscordMC-0.0.8.dist-info/RECORD
